CIRIquant/__init__.py
CIRIquant/circ.py
CIRIquant/coeff.py
CIRIquant/de.py
CIRIquant/logger.py
CIRIquant/main.py
CIRIquant/pipeline.py
CIRIquant/prep_CIRIquant.py
CIRIquant/replicate.py
CIRIquant/utils.py
CIRIquant/version.py
libs/CIRI2.pl
libs/CIRI_DE.R
libs/__init__.py
CIRIquant-1.1.3.dist-info/LICENSE
CIRIquant-1.1.3.dist-info/METADATA
CIRIquant-1.1.3.dist-info/WHEEL
CIRIquant-1.1.3.dist-info/entry_points.txt
CIRIquant-1.1.3.dist-info/top_level.txt
CIRIquant-1.1.3.dist-info/RECORD
