Metadata-Version: 2.1
Name: CIRIquant
Version: 1.1.3
Summary: circular RNA quantification pipeline
Home-page: https://github.com/bioinfo-biols/CIRIquant
Author: Jinyang Zhang
Author-email: zhangjinyang@biols.ac.cn
Maintainer: Jinyang Zhang
Maintainer-email: zhangjinyang@biols.ac.cn
License: MIT
Keywords: circRNA
Platform: UNKNOWN
Classifier: License :: OSI Approved :: MIT License
Classifier: Programming Language :: Python
Classifier: Intended Audience :: Developers
Classifier: Operating System :: OS Independent
Requires-Dist: argparse (>=1.2.1)
Requires-Dist: PyYAML (==5.4)
Requires-Dist: pysam (==0.15.2)
Requires-Dist: numpy (==1.16.4)
Requires-Dist: scipy (==1.2.2)
Requires-Dist: scikit-learn (==0.20.3)
Requires-Dist: numexpr (==2.6.9)
